[{"symbol":"ACC","current_candlestick_pattern":"","no_of_dry_day":"3","percentage_increase_volume":"0.00","previous_candlestick_pattern":"Bearish One Black Crow","previous_candlestick_pattern_date":"2018-09-04 00:00:00","current_volume":"416648","average_volume":"674229","executed":"2018-09-05 12:55:30"}, {"symbol":"ADANIENT","current_candlestick_pattern":"Bullish Engulfing Pattern ","no_of_dry_day":"0","percentage_increase_volume":"0.00","previous_candlestick_pattern":"Bearish Engulfing Pattern","previous_candlestick_pattern_date":"2018-09-03 00:00:00","current_volume":"15283362","average_volume":"20250693","executed":"2018-09-05 12:55:34"}, {"symbol":"ADANIPORTS","current_candlestick_pattern":"Paper Umbrella ","no_of_dry_day":"2","percentage_increase_volume":"0.00","previous_candlestick_pattern":"Bearish Engulfing Pattern","previous_candlestick_pattern_date":"2018-09-04 00:00:00","current_volume":"1183641","average_volume":"2890360","executed":"2018-09-05 12:55:30"}, {"symbol":"ADANIPOWER","current_candlestick_pattern":"","no_of_dry_day":"4","percentage_increase_volume":"0.00","previous_candlestick_pattern":"Bearish Engulfing Pattern","previous_candlestick_pattern_date":"2018-09-03 00:00:00","current_volume":"19942902","average_volume":"34028929","executed":"2018-09-05 12:55:34"}, {"symbol":"AJANTPHARM","current_candlestick_pattern":"Shooting Star ","no_of_dry_day":"2","percentage_increase_volume":"0.00","previous_candlestick_pattern":"Bearish Engulfing Pattern","previous_candlestick_pattern_date":"2018-09-03 00:00:00","current_volume":"236316","average_volume":"371612","executed":"2018-09-05 12:55:34"}, {"symbol":"ALBK","current_candlestick_pattern":"","no_of_dry_day":"0","percentage_increase_volume":"0.00","previous_candlestick_pattern":"Shooting Star","previous_candlestick_pattern_date":"2018-09-03 00:00:00","current_volume":"1752361","average_volume":"4027842","executed":"2018-09-05 12:55:34"}, {"symbol":"AMARAJABAT","current_candlestick_pattern":"","no_of_dry_day":"8","percentage_increase_volume":"0.00","previous_candlestick_pattern":"Shooting Star","previous_candlestick_pattern_date":"2018-09-03 00:00:00","current_volume":"173045","average_volume":"433885","executed":"2018-09-05 12:55:30"}, {"symbol":"AMBUJACEM","current_candlestick_pattern":"","no_of_dry_day":"0","percentage_increase_volume":"0.00","previous_candlestick_pattern":"Shooting Star","previous_candlestick_pattern_date":"2018-09-04 00:00:00","current_volume":"2225724","average_volume":"2751773","executed":"2018-09-05 12:55:30"}, {"symbol":"ANDHRABANK","current_candlestick_pattern":"","no_of_dry_day":"0","percentage_increase_volume":"19.62","previous_candlestick_pattern":"Bearish One Black Crow","previous_candlestick_pattern_date":"2018-09-04 00:00:00","current_volume":"4531689","average_volume":"3788509","executed":"2018-09-05 12:55:34"}, {"symbol":"APOLLOHOSP","current_candlestick_pattern":"","no_of_dry_day":"4","percentage_increase_volume":"0.00","previous_candlestick_pattern":"Paper Umbrella","previous_candlestick_pattern_date":"2018-09-04 00:00:00","current_volume":"607264","average_volume":"1204454","executed":"2018-09-05 12:55:34"}, {"symbol":"APOLLOTYRE","current_candlestick_pattern":"Shooting Star ","no_of_dry_day":"0","percentage_increase_volume":"0.00","previous_candlestick_pattern":"Bearish Engulfing Pattern","previous_candlestick_pattern_date":"2018-09-03 00:00:00","current_volume":"1230292","average_volume":"3284030","executed":"2018-09-05 12:55:34"}, {"symbol":"ARVIND","current_candlestick_pattern":"","no_of_dry_day":"0","percentage_increase_volume":"0.00","previous_candlestick_pattern":"Shooting Star","previous_candlestick_pattern_date":"2018-09-03 00:00:00","current_volume":"1133491","average_volume":"1591862","executed":"2018-09-05 12:55:30"}, {"symbol":"ASHOKLEY","current_candlestick_pattern":"","no_of_dry_day":"0","percentage_increase_volume":"0.00","previous_candlestick_pattern":"","previous_candlestick_pattern_date":"0000-00-00 00:00:00","current_volume":"10161206","average_volume":"19503129","executed":"2018-09-05 12:55:34"}, {"symbol":"ASIANPAINT","current_candlestick_pattern":"","no_of_dry_day":"0","percentage_increase_volume":"0.00","previous_candlestick_pattern":"Bearish Engulfing Pattern","previous_candlestick_pattern_date":"2018-08-29 00:00:00","current_volume":"559688","average_volume":"983419","executed":"2018-09-05 12:55:30"}, {"symbol":"AUROPHARMA","current_candlestick_pattern":"Bullish Harami Pattern ","no_of_dry_day":"2","percentage_increase_volume":"0.00","previous_candlestick_pattern":"Bullish One White Soldier","previous_candlestick_pattern_date":"2018-08-31 00:00:00","current_volume":"1581767","average_volume":"3696693","executed":"2018-09-05 12:55:30"}, {"symbol":"AXISBANK","current_candlestick_pattern":"Bearish Harami Pattern ","no_of_dry_day":"3","percentage_increase_volume":"0.00","previous_candlestick_pattern":"Piercing Pattern","previous_candlestick_pattern_date":"2018-09-04 00:00:00","current_volume":"3701302","average_volume":"10534778","executed":"2018-09-05 12:55:30"}, {"symbol":"BAJAJ-AUTO","current_candlestick_pattern":"Piercing Pattern ","no_of_dry_day":"0","percentage_increase_volume":"0.00","previous_candlestick_pattern":"Bearish Engulfing Pattern","previous_candlestick_pattern_date":"2018-09-04 00:00:00","current_volume":"233688","average_volume":"467481","executed":"2018-09-05 12:55:30"}, {"symbol":"BAJAJFINSV","current_candlestick_pattern":"","no_of_dry_day":"0","percentage_increase_volume":"0.00","previous_candlestick_pattern":"Bearish Engulfing Pattern","previous_candlestick_pattern_date":"2018-08-23 00:00:00","current_volume":"86012","average_volume":"179007","executed":"2018-09-05 12:55:30"}, {"symbol":"BAJFINANCE","current_candlestick_pattern":"Bearish One Black Crow ","no_of_dry_day":"0","percentage_increase_volume":"0.00","previous_candlestick_pattern":"Bearish Engulfing Pattern","previous_candlestick_pattern_date":"2018-08-30 00:00:00","current_volume":"764380","average_volume":"1531437","executed":"2018-09-05 12:55:30"}, {"symbol":"BALKRISIND","current_candlestick_pattern":"","no_of_dry_day":"0","percentage_increase_volume":"13.65","previous_candlestick_pattern":"Bearish Engulfing Pattern","previous_candlestick_pattern_date":"2018-08-30 00:00:00","current_volume":"1694534","average_volume":"1490984","executed":"2018-09-05 12:55:30"}, {"symbol":"BALRAMCHIN","current_candlestick_pattern":"Bullish Harami Pattern ","no_of_dry_day":"0","percentage_increase_volume":"0.00","previous_candlestick_pattern":"Bullish Harami Pattern","previous_candlestick_pattern_date":"2018-08-29 00:00:00","current_volume":"1546850","average_volume":"3630537","executed":"2018-09-05 12:55:34"}, {"symbol":"BANKBARODA","current_candlestick_pattern":"","no_of_dry_day":"1","percentage_increase_volume":"0.00","previous_candlestick_pattern":"Bullish Harami Pattern","previous_candlestick_pattern_date":"2018-08-29 00:00:00","current_volume":"6906268","average_volume":"13719217","executed":"2018-09-05 12:55:34"}, {"symbol":"BANKINDIA","current_candlestick_pattern":"","no_of_dry_day":"2","percentage_increase_volume":"0.00","previous_candlestick_pattern":"Bullish One White Soldier","previous_candlestick_pattern_date":"2018-08-29 00:00:00","current_volume":"5236095","average_volume":"8697221","executed":"2018-09-05 12:55:34"}, {"symbol":"BATAINDIA","current_candlestick_pattern":"","no_of_dry_day":"5","percentage_increase_volume":"0.00","previous_candlestick_pattern":"Bullish Engulfing Pattern","previous_candlestick_pattern_date":"2018-08-28 00:00:00","current_volume":"400487","average_volume":"997538","executed":"2018-09-05 12:55:30"}, {"symbol":"BEL","current_candlestick_pattern":"","no_of_dry_day":"0","percentage_increase_volume":"528.18","previous_candlestick_pattern":"Shooting Star","previous_candlestick_pattern_date":"2018-08-31 00:00:00","current_volume":"80604901","average_volume":"12831467","executed":"2018-09-05 12:55:30"}, {"symbol":"BEML","current_candlestick_pattern":"","no_of_dry_day":"0","percentage_increase_volume":"83.09","previous_candlestick_pattern":"","previous_candlestick_pattern_date":"0000-00-00 00:00:00","current_volume":"1824782","average_volume":"996684","executed":"2018-09-05 12:55:34"}, {"symbol":"BERGEPAINT","current_candlestick_pattern":"","no_of_dry_day":"0","percentage_increase_volume":"0.00","previous_candlestick_pattern":"Bearish One Black Crow","previous_candlestick_pattern_date":"2018-08-30 00:00:00","current_volume":"459832","average_volume":"879216","executed":"2018-09-05 12:55:30"}, {"symbol":"BHARATFIN","current_candlestick_pattern":"","no_of_dry_day":"0","percentage_increase_volume":"0.00","previous_candlestick_pattern":"Bearish Engulfing Pattern","previous_candlestick_pattern_date":"2018-08-28 00:00:00","current_volume":"512617","average_volume":"559148","executed":"2018-09-05 12:55:30"}, {"symbol":"BHARATFORG","current_candlestick_pattern":"","no_of_dry_day":"0","percentage_increase_volume":"0.00","previous_candlestick_pattern":"Bearish Engulfing Pattern","previous_candlestick_pattern_date":"2018-09-03 00:00:00","current_volume":"607847","average_volume":"1751612","executed":"2018-09-05 12:55:30"}, {"symbol":"BHARTIARTL","current_candlestick_pattern":"","no_of_dry_day":"2","percentage_increase_volume":"0.00","previous_candlestick_pattern":"Bullish One White Soldier","previous_candlestick_pattern_date":"2018-08-30 00:00:00","current_volume":"3442987","average_volume":"4498496","executed":"2018-09-05 12:55:30"}, {"symbol":"BHEL","current_candlestick_pattern":"","no_of_dry_day":"4","percentage_increase_volume":"0.00","previous_candlestick_pattern":"Bearish Engulfing Pattern","previous_candlestick_pattern_date":"2018-09-04 00:00:00","current_volume":"7577995","average_volume":"12417701","executed":"2018-09-05 12:55:30"}, {"symbol":"BIOCON","current_candlestick_pattern":"Bullish One White Soldier ","no_of_dry_day":"1","percentage_increase_volume":"103.52","previous_candlestick_pattern":"Bullish One White Soldier","previous_candlestick_pattern_date":"2018-08-31 00:00:00","current_volume":"3615166","average_volume":"1776295","executed":"2018-09-05 12:55:30"}, {"symbol":"BOSCHLTD","current_candlestick_pattern":"","no_of_dry_day":"1","percentage_increase_volume":"0.00","previous_candlestick_pattern":"Bullish Harami Pattern","previous_candlestick_pattern_date":"2018-08-28 00:00:00","current_volume":"9544","average_volume":"34893","executed":"2018-09-05 12:55:30"}, {"symbol":"BPCL","current_candlestick_pattern":"Shooting Star ","no_of_dry_day":"2","percentage_increase_volume":"0.00","previous_candlestick_pattern":"Bullish Engulfing Pattern","previous_candlestick_pattern_date":"2018-08-29 00:00:00","current_volume":"2555116","average_volume":"4080319","executed":"2018-09-05 12:55:30"}, {"symbol":"BRITANNIA","current_candlestick_pattern":"","no_of_dry_day":"0","percentage_increase_volume":"42.72","previous_candlestick_pattern":"Bearish Engulfing Pattern","previous_candlestick_pattern_date":"2018-09-03 00:00:00","current_volume":"181151","average_volume":"126927","executed":"2018-09-05 12:55:30"}, {"symbol":"CADILAHC","current_candlestick_pattern":"Shooting Star ","no_of_dry_day":"1","percentage_increase_volume":"0.00","previous_candlestick_pattern":"Bearish Evening Star Pattern","previous_candlestick_pattern_date":"2018-09-04 00:00:00","current_volume":"1382269","average_volume":"3393327","executed":"2018-09-05 12:55:30"}, {"symbol":"CANBK","current_candlestick_pattern":"","no_of_dry_day":"0","percentage_increase_volume":"0.00","previous_candlestick_pattern":"Shooting Star","previous_candlestick_pattern_date":"2018-09-03 00:00:00","current_volume":"4089171","average_volume":"6666998","executed":"2018-09-05 12:55:34"}, {"symbol":"CANFINHOME","current_candlestick_pattern":"","no_of_dry_day":"1","percentage_increase_volume":"0.00","previous_candlestick_pattern":"Bearish Engulfing Pattern","previous_candlestick_pattern_date":"2018-09-04 00:00:00","current_volume":"547396","average_volume":"783609","executed":"2018-09-05 12:55:30"}, {"symbol":"CAPF","current_candlestick_pattern":"","no_of_dry_day":"0","percentage_increase_volume":"0.00","previous_candlestick_pattern":"Bearish One Black Crow","previous_candlestick_pattern_date":"2018-09-04 00:00:00","current_volume":"482942","average_volume":"758372","executed":"2018-09-05 12:55:34"}, {"symbol":"CASTROLIND","current_candlestick_pattern":"Piercing Pattern ","no_of_dry_day":"0","percentage_increase_volume":"0.00","previous_candlestick_pattern":"Bearish One Black Crow","previous_candlestick_pattern_date":"2018-08-30 00:00:00","current_volume":"828854","average_volume":"1282175","executed":"2018-09-05 12:55:30"}, {"symbol":"CEATLTD","current_candlestick_pattern":"Shooting Star Bullish Harami Pattern ","no_of_dry_day":"0","percentage_increase_volume":"0.00","previous_candlestick_pattern":"Bearish Engulfing Pattern","previous_candlestick_pattern_date":"2018-09-04 00:00:00","current_volume":"451759","average_volume":"512310","executed":"2018-09-05 12:55:30"}, {"symbol":"CENTURYTEX","current_candlestick_pattern":"","no_of_dry_day":"1","percentage_increase_volume":"0.00","previous_candlestick_pattern":"Bullish Engulfing Pattern","previous_candlestick_pattern_date":"2018-08-31 00:00:00","current_volume":"409351","average_volume":"839843","executed":"2018-09-05 12:55:30"}, {"symbol":"CESC","current_candlestick_pattern":"","no_of_dry_day":"1","percentage_increase_volume":"0.00","previous_candlestick_pattern":"Bullish One White Soldier","previous_candlestick_pattern_date":"2018-09-03 00:00:00","current_volume":"368678","average_volume":"813388","executed":"2018-09-05 12:55:30"}, {"symbol":"CGPOWER","current_candlestick_pattern":"Paper Umbrella ","no_of_dry_day":"0","percentage_increase_volume":"0.00","previous_candlestick_pattern":"Bullish One White Soldier","previous_candlestick_pattern_date":"2018-08-30 00:00:00","current_volume":"2769293","average_volume":"3303799","executed":"2018-09-05 12:55:34"}, {"symbol":"CHENNPETRO","current_candlestick_pattern":"","no_of_dry_day":"2","percentage_increase_volume":"0.00","previous_candlestick_pattern":"Bearish Engulfing Pattern","previous_candlestick_pattern_date":"2018-09-03 00:00:00","current_volume":"183199","average_volume":"391503","executed":"2018-09-05 12:55:30"}, {"symbol":"CHOLAFIN","current_candlestick_pattern":"Shooting Star ","no_of_dry_day":"0","percentage_increase_volume":"0.00","previous_candlestick_pattern":"Bearish One Black Crow","previous_candlestick_pattern_date":"2018-09-04 00:00:00","current_volume":"82555","average_volume":"221016","executed":"2018-09-05 12:55:30"}, {"symbol":"CIPLA","current_candlestick_pattern":"","no_of_dry_day":"2","percentage_increase_volume":"0.00","previous_candlestick_pattern":"Bearish Engulfing Pattern","previous_candlestick_pattern_date":"2018-09-03 00:00:00","current_volume":"1179847","average_volume":"2388784","executed":"2018-09-05 12:55:34"}, {"symbol":"COALINDIA","current_candlestick_pattern":"","no_of_dry_day":"5","percentage_increase_volume":"0.00","previous_candlestick_pattern":"Bearish Engulfing Pattern","previous_candlestick_pattern_date":"2018-09-04 00:00:00","current_volume":"2746490","average_volume":"3126627","executed":"2018-09-05 12:55:34"}, {"symbol":"COLPAL","current_candlestick_pattern":"Shooting Star ","no_of_dry_day":"1","percentage_increase_volume":"0.00","previous_candlestick_pattern":"Bearish Engulfing Pattern","previous_candlestick_pattern_date":"2018-09-04 00:00:00","current_volume":"224262","average_volume":"615140","executed":"2018-09-05 12:55:30"}, {"symbol":"CONCOR","current_candlestick_pattern":"","no_of_dry_day":"0","percentage_increase_volume":"0.00","previous_candlestick_pattern":"Bullish One White Soldier","previous_candlestick_pattern_date":"2018-08-31 00:00:00","current_volume":"262101","average_volume":"520944","executed":"2018-09-05 12:55:34"}, {"symbol":"CUMMINSIND","current_candlestick_pattern":"","no_of_dry_day":"8","percentage_increase_volume":"0.00","previous_candlestick_pattern":"Paper Umbrella","previous_candlestick_pattern_date":"2018-08-30 00:00:00","current_volume":"166442","average_volume":"562239","executed":"2018-09-05 12:55:30"}, {"symbol":"DABUR","current_candlestick_pattern":"Piercing Pattern ","no_of_dry_day":"0","percentage_increase_volume":"0.00","previous_candlestick_pattern":"Piercing Pattern","previous_candlestick_pattern_date":"2018-08-30 00:00:00","current_volume":"2461512","average_volume":"4033274","executed":"2018-09-05 12:55:30"}, {"symbol":"DALMIABHA","current_candlestick_pattern":"","no_of_dry_day":"2","percentage_increase_volume":"0.00","previous_candlestick_pattern":"Bearish Harami Pattern","previous_candlestick_pattern_date":"2018-08-31 00:00:00","current_volume":"36823","average_volume":"100933","executed":"2018-09-05 12:55:30"}, {"symbol":"DCBBANK","current_candlestick_pattern":"","no_of_dry_day":"0","percentage_increase_volume":"1.61","previous_candlestick_pattern":"Paper Umbrella","previous_candlestick_pattern_date":"2018-09-04 00:00:00","current_volume":"1430482","average_volume":"1407868","executed":"2018-09-05 12:55:30"}, {"symbol":"DHFL","current_candlestick_pattern":"","no_of_dry_day":"1","percentage_increase_volume":"0.00","previous_candlestick_pattern":"Bearish Engulfing Pattern","previous_candlestick_pattern_date":"2018-09-04 00:00:00","current_volume":"1933240","average_volume":"3213328","executed":"2018-09-05 12:55:30"}, {"symbol":"DISHTV","current_candlestick_pattern":"Shooting Star ","no_of_dry_day":"0","percentage_increase_volume":"0.00","previous_candlestick_pattern":"Shooting Star","previous_candlestick_pattern_date":"2018-09-03 00:00:00","current_volume":"1762009","average_volume":"3918741","executed":"2018-09-05 12:55:34"}, {"symbol":"DIVISLAB","current_candlestick_pattern":"Shooting Star ","no_of_dry_day":"4","percentage_increase_volume":"0.00","previous_candlestick_pattern":"Bearish Engulfing Pattern","previous_candlestick_pattern_date":"2018-09-03 00:00:00","current_volume":"531230","average_volume":"1026936","executed":"2018-09-05 12:55:30"}, {"symbol":"DLF","current_candlestick_pattern":"","no_of_dry_day":"0","percentage_increase_volume":"0.00","previous_candlestick_pattern":"Paper Umbrella","previous_candlestick_pattern_date":"2018-08-31 00:00:00","current_volume":"4145018","average_volume":"7563406","executed":"2018-09-05 12:55:34"}, {"symbol":"DRREDDY","current_candlestick_pattern":"","no_of_dry_day":"1","percentage_increase_volume":"0.00","previous_candlestick_pattern":"Bullish One White Soldier","previous_candlestick_pattern_date":"2018-08-31 00:00:00","current_volume":"723009","average_volume":"1190625","executed":"2018-09-05 12:55:34"}, {"symbol":"EICHERMOT","current_candlestick_pattern":"","no_of_dry_day":"1","percentage_increase_volume":"0.00","previous_candlestick_pattern":"Bullish Harami Pattern","previous_candlestick_pattern_date":"2018-08-31 00:00:00","current_volume":"17180","average_volume":"48670","executed":"2018-09-05 12:55:30"}, {"symbol":"ENGINERSIN","current_candlestick_pattern":"","no_of_dry_day":"0","percentage_increase_volume":"23.96","previous_candlestick_pattern":"Paper Umbrella","previous_candlestick_pattern_date":"2018-08-24 00:00:00","current_volume":"3182156","average_volume":"2567062","executed":"2018-09-05 12:55:30"}, {"symbol":"EQUITAS","current_candlestick_pattern":"","no_of_dry_day":"3","percentage_increase_volume":"0.00","previous_candlestick_pattern":"Bearish Engulfing Pattern","previous_candlestick_pattern_date":"2018-09-04 00:00:00","current_volume":"943564","average_volume":"3108899","executed":"2018-09-05 12:55:30"}, {"symbol":"ESCORTS","current_candlestick_pattern":"","no_of_dry_day":"0","percentage_increase_volume":"13.34","previous_candlestick_pattern":"Bullish One White Soldier","previous_candlestick_pattern_date":"2018-08-28 00:00:00","current_volume":"1317046","average_volume":"1162041","executed":"2018-09-05 12:55:30"}, {"symbol":"EXIDEIND","current_candlestick_pattern":"","no_of_dry_day":"3","percentage_increase_volume":"0.00","previous_candlestick_pattern":"Bearish Engulfing Pattern","previous_candlestick_pattern_date":"2018-08-24 00:00:00","current_volume":"471614","average_volume":"1712544","executed":"2018-09-05 12:55:30"}, {"symbol":"FEDERALBNK","current_candlestick_pattern":"","no_of_dry_day":"9","percentage_increase_volume":"0.00","previous_candlestick_pattern":"Bullish One White Soldier","previous_candlestick_pattern_date":"2018-08-29 00:00:00","current_volume":"6018970","average_volume":"14774639","executed":"2018-09-05 12:55:34"}, {"symbol":"GAIL","current_candlestick_pattern":"Shooting Star Bullish Harami Pattern ","no_of_dry_day":"3","percentage_increase_volume":"0.00","previous_candlestick_pattern":"Bullish One White Soldier","previous_candlestick_pattern_date":"2018-08-30 00:00:00","current_volume":"2161126","average_volume":"4837804","executed":"2018-09-05 12:55:30"}, {"symbol":"GLENMARK","current_candlestick_pattern":"Bullish One White Soldier Piercing Pattern ","no_of_dry_day":"2","percentage_increase_volume":"0.00","previous_candlestick_pattern":"Bearish Engulfing Pattern","previous_candlestick_pattern_date":"2018-09-03 00:00:00","current_volume":"390483","average_volume":"1142066","executed":"2018-09-05 12:55:30"}, {"symbol":"GMRINFRA","current_candlestick_pattern":"","no_of_dry_day":"1","percentage_increase_volume":"0.00","previous_candlestick_pattern":"","previous_candlestick_pattern_date":"0000-00-00 00:00:00","current_volume":"17578763","average_volume":"31474003","executed":"2018-09-05 12:55:34"}, {"symbol":"GODFRYPHLP","current_candlestick_pattern":"","no_of_dry_day":"3","percentage_increase_volume":"0.00","previous_candlestick_pattern":"Bearish Harami Pattern","previous_candlestick_pattern_date":"2018-08-31 00:00:00","current_volume":"29238","average_volume":"91551","executed":"2018-09-05 12:55:30"}, {"symbol":"GODREJCP","current_candlestick_pattern":"","no_of_dry_day":"0","percentage_increase_volume":"0.00","previous_candlestick_pattern":"Bearish Engulfing Pattern","previous_candlestick_pattern_date":"2018-09-03 00:00:00","current_volume":"388011","average_volume":"804794","executed":"2018-09-05 12:55:30"}, {"symbol":"GODREJIND","current_candlestick_pattern":"","no_of_dry_day":"2","percentage_increase_volume":"0.00","previous_candlestick_pattern":"Bearish Engulfing Pattern","previous_candlestick_pattern_date":"2018-09-03 00:00:00","current_volume":"123538","average_volume":"458135","executed":"2018-09-05 12:55:30"}, {"symbol":"GRANULES","current_candlestick_pattern":"Shooting Star Piercing Pattern ","no_of_dry_day":"2","percentage_increase_volume":"0.00","previous_candlestick_pattern":"Bullish Harami Pattern","previous_candlestick_pattern_date":"2018-08-30 00:00:00","current_volume":"1488981","average_volume":"3211266","executed":"2018-09-05 12:55:30"}, {"symbol":"GRASIM","current_candlestick_pattern":"","no_of_dry_day":"6","percentage_increase_volume":"0.00","previous_candlestick_pattern":"Bearish Engulfing Pattern","previous_candlestick_pattern_date":"2018-09-03 00:00:00","current_volume":"403865","average_volume":"1145386","executed":"2018-09-05 12:55:30"}, {"symbol":"GSFC","current_candlestick_pattern":"","no_of_dry_day":"1","percentage_increase_volume":"0.00","previous_candlestick_pattern":"Bearish One Black Crow","previous_candlestick_pattern_date":"2018-09-04 00:00:00","current_volume":"1539917","average_volume":"2275054","executed":"2018-09-05 12:55:30"}, {"symbol":"HAVELLS","current_candlestick_pattern":"","no_of_dry_day":"0","percentage_increase_volume":"12.10","previous_candlestick_pattern":"Bearish One Black Crow","previous_candlestick_pattern_date":"2018-09-03 00:00:00","current_volume":"1312420","average_volume":"1170758","executed":"2018-09-05 12:55:30"}, {"symbol":"HCC","current_candlestick_pattern":"","no_of_dry_day":"1","percentage_increase_volume":"0.00","previous_candlestick_pattern":"Paper Umbrella","previous_candlestick_pattern_date":"2018-08-31 00:00:00","current_volume":"15969023","average_volume":"20041497","executed":"2018-09-05 12:55:34"}, {"symbol":"HCLTECH","current_candlestick_pattern":"","no_of_dry_day":"0","percentage_increase_volume":"0.00","previous_candlestick_pattern":"Bullish One White Soldier","previous_candlestick_pattern_date":"2018-09-04 00:00:00","current_volume":"1337471","average_volume":"2170627","executed":"2018-09-05 12:55:30"}, {"symbol":"HDFC","current_candlestick_pattern":"Bearish One Black Crow ","no_of_dry_day":"0","percentage_increase_volume":"0.00","previous_candlestick_pattern":"Bullish Engulfing Pattern","previous_candlestick_pattern_date":"2018-09-04 00:00:00","current_volume":"1535084","average_volume":"2333868","executed":"2018-09-05 12:55:30"}, {"symbol":"HDFCBANK","current_candlestick_pattern":"","no_of_dry_day":"2","percentage_increase_volume":"0.00","previous_candlestick_pattern":"Bearish Engulfing Pattern","previous_candlestick_pattern_date":"2018-09-04 00:00:00","current_volume":"705479","average_volume":"2748105","executed":"2018-09-05 12:55:30"}, {"symbol":"HEROMOTOCO","current_candlestick_pattern":"","no_of_dry_day":"2","percentage_increase_volume":"0.00","previous_candlestick_pattern":"Bullish Engulfing Pattern","previous_candlestick_pattern_date":"2018-08-31 00:00:00","current_volume":"165594","average_volume":"283090","executed":"2018-09-05 12:55:30"}, {"symbol":"HEXAWARE","current_candlestick_pattern":"Bullish One White Soldier ","no_of_dry_day":"7","percentage_increase_volume":"0.00","previous_candlestick_pattern":"Bearish Engulfing Pattern","previous_candlestick_pattern_date":"2018-09-03 00:00:00","current_volume":"2845540","average_volume":"9957786","executed":"2018-09-05 12:55:30"}, {"symbol":"HINDALCO","current_candlestick_pattern":"Piercing Pattern ","no_of_dry_day":"4","percentage_increase_volume":"0.00","previous_candlestick_pattern":"Piercing Pattern","previous_candlestick_pattern_date":"2018-09-03 00:00:00","current_volume":"4975784","average_volume":"9607154","executed":"2018-09-05 12:55:34"}, {"symbol":"HINDPETRO","current_candlestick_pattern":"","no_of_dry_day":"2","percentage_increase_volume":"0.00","previous_candlestick_pattern":"Bearish One Black Crow","previous_candlestick_pattern_date":"2018-09-04 00:00:00","current_volume":"2994961","average_volume":"4666609","executed":"2018-09-05 12:55:30"}, {"symbol":"HINDUNILVR","current_candlestick_pattern":"","no_of_dry_day":"0","percentage_increase_volume":"0.35","previous_candlestick_pattern":"Bearish Engulfing Pattern","previous_candlestick_pattern_date":"2018-09-03 00:00:00","current_volume":"1467757","average_volume":"1462566","executed":"2018-09-05 12:55:30"}, {"symbol":"HINDZINC","current_candlestick_pattern":"Piercing Pattern ","no_of_dry_day":"3","percentage_increase_volume":"5.00","previous_candlestick_pattern":"Shooting Star","previous_candlestick_pattern_date":"2018-08-29 00:00:00","current_volume":"1061717","average_volume":"1011155","executed":"2018-09-05 12:55:30"}, {"symbol":"IBULHSGFIN","current_candlestick_pattern":"","no_of_dry_day":"0","percentage_increase_volume":"0.00","previous_candlestick_pattern":"Bullish One White Soldier","previous_candlestick_pattern_date":"2018-08-27 00:00:00","current_volume":"618554","average_volume":"797264","executed":"2018-09-05 12:55:30"}, {"symbol":"ICICIBANK","current_candlestick_pattern":"","no_of_dry_day":"6","percentage_increase_volume":"0.00","previous_candlestick_pattern":"Bearish Harami Pattern","previous_candlestick_pattern_date":"2018-08-31 00:00:00","current_volume":"6811507","average_volume":"17735386","executed":"2018-09-05 12:55:30"}, {"symbol":"ICICIPRULI","current_candlestick_pattern":"","no_of_dry_day":"2","percentage_increase_volume":"57.29","previous_candlestick_pattern":"Bearish One Black Crow","previous_candlestick_pattern_date":"2018-09-04 00:00:00","current_volume":"1586120","average_volume":"1008419","executed":"2018-09-05 12:55:30"}, {"symbol":"IDBI","current_candlestick_pattern":"","no_of_dry_day":"0","percentage_increase_volume":"0.00","previous_candlestick_pattern":"Piercing Pattern","previous_candlestick_pattern_date":"2018-08-29 00:00:00","current_volume":"5038953","average_volume":"12776632","executed":"2018-09-05 12:55:34"}, {"symbol":"IDEA","current_candlestick_pattern":"","no_of_dry_day":"1","percentage_increase_volume":"0.00","previous_candlestick_pattern":"Bearish Engulfing Pattern","previous_candlestick_pattern_date":"2018-09-04 00:00:00","current_volume":"18351341","average_volume":"28302510","executed":"2018-09-05 12:55:34"}, {"symbol":"IDFC","current_candlestick_pattern":"Shooting Star ","no_of_dry_day":"3","percentage_increase_volume":"0.00","previous_candlestick_pattern":"Piercing Pattern","previous_candlestick_pattern_date":"2018-08-28 00:00:00","current_volume":"1485278","average_volume":"3887132","executed":"2018-09-05 12:55:34"}, {"symbol":"IDFCBANK","current_candlestick_pattern":"","no_of_dry_day":"0","percentage_increase_volume":"0.00","previous_candlestick_pattern":"Shooting Star","previous_candlestick_pattern_date":"2018-09-03 00:00:00","current_volume":"5683840","average_volume":"9043004","executed":"2018-09-05 12:55:34"}, {"symbol":"IFCI","current_candlestick_pattern":"","no_of_dry_day":"0","percentage_increase_volume":"0.00","previous_candlestick_pattern":"Bearish One Black Crow","previous_candlestick_pattern_date":"2018-09-04 00:00:00","current_volume":"3658269","average_volume":"7042275","executed":"2018-09-05 12:55:34"}, {"symbol":"IGL","current_candlestick_pattern":"","no_of_dry_day":"1","percentage_increase_volume":"36.45","previous_candlestick_pattern":"Bullish One White Soldier","previous_candlestick_pattern_date":"2018-08-29 00:00:00","current_volume":"2434542","average_volume":"1784167","executed":"2018-09-05 12:55:30"}, {"symbol":"INDIACEM","current_candlestick_pattern":"","no_of_dry_day":"0","percentage_increase_volume":"0.00","previous_candlestick_pattern":"Bearish Engulfing Pattern","previous_candlestick_pattern_date":"2018-08-28 00:00:00","current_volume":"2847580","average_volume":"5762014","executed":"2018-09-05 12:55:30"}, {"symbol":"INDIANB","current_candlestick_pattern":"","no_of_dry_day":"1","percentage_increase_volume":"0.00","previous_candlestick_pattern":"Piercing Pattern","previous_candlestick_pattern_date":"2018-08-29 00:00:00","current_volume":"787236","average_volume":"1077576","executed":"2018-09-05 12:55:34"}, {"symbol":"INDIGO","current_candlestick_pattern":"","no_of_dry_day":"0","percentage_increase_volume":"24.86","previous_candlestick_pattern":"Bearish One Black Crow","previous_candlestick_pattern_date":"2018-09-04 00:00:00","current_volume":"2016548","average_volume":"1614993","executed":"2018-09-05 12:55:30"}, {"symbol":"INDUSINDBK","current_candlestick_pattern":"","no_of_dry_day":"0","percentage_increase_volume":"0.00","previous_candlestick_pattern":"Bearish Harami Pattern","previous_candlestick_pattern_date":"2018-09-03 00:00:00","current_volume":"348604","average_volume":"1173727","executed":"2018-09-05 12:55:30"}, {"symbol":"INFIBEAM","current_candlestick_pattern":"","no_of_dry_day":"3","percentage_increase_volume":"0.00","previous_candlestick_pattern":"Bearish Engulfing Pattern","previous_candlestick_pattern_date":"2018-09-04 00:00:00","current_volume":"1034501","average_volume":"5904134","executed":"2018-09-05 12:55:30"}, {"symbol":"INFRATEL","current_candlestick_pattern":"","no_of_dry_day":"4","percentage_increase_volume":"0.00","previous_candlestick_pattern":"Bearish Engulfing Pattern","previous_candlestick_pattern_date":"2018-09-04 00:00:00","current_volume":"863963","average_volume":"3114762","executed":"2018-09-05 12:55:30"}, {"symbol":"INFY","current_candlestick_pattern":"","no_of_dry_day":"0","percentage_increase_volume":"0.00","previous_candlestick_pattern":"Bullish Harami Pattern","previous_candlestick_pattern_date":"2018-08-30 00:00:00","current_volume":"5227579","average_volume":"5424104","executed":"2018-09-05 12:55:34"}, {"symbol":"IOC","current_candlestick_pattern":"","no_of_dry_day":"3","percentage_increase_volume":"0.00","previous_candlestick_pattern":"Piercing Pattern","previous_candlestick_pattern_date":"2018-08-31 00:00:00","current_volume":"3470775","average_volume":"5681724","executed":"2018-09-05 12:55:34"}, {"symbol":"IRB","current_candlestick_pattern":"Piercing Pattern ","no_of_dry_day":"0","percentage_increase_volume":"74.49","previous_candlestick_pattern":"Bearish Engulfing Pattern","previous_candlestick_pattern_date":"2018-09-03 00:00:00","current_volume":"4405221","average_volume":"2524567","executed":"2018-09-05 12:55:34"}, {"symbol":"ITC","current_candlestick_pattern":"Bullish One White Soldier ","no_of_dry_day":"2","percentage_increase_volume":"0.00","previous_candlestick_pattern":"Bullish Harami Pattern","previous_candlestick_pattern_date":"2018-08-29 00:00:00","current_volume":"5144689","average_volume":"10749331","executed":"2018-09-05 12:55:30"}, {"symbol":"JETAIRWAYS","current_candlestick_pattern":"Shooting Star ","no_of_dry_day":"5","percentage_increase_volume":"0.00","previous_candlestick_pattern":"Bearish One Black Crow","previous_candlestick_pattern_date":"2018-09-04 00:00:00","current_volume":"6034600","average_volume":"8019263","executed":"2018-09-05 12:55:30"}, {"symbol":"JINDALSTEL","current_candlestick_pattern":"","no_of_dry_day":"0","percentage_increase_volume":"0.00","previous_candlestick_pattern":"Shooting Star","previous_candlestick_pattern_date":"2018-09-03 00:00:00","current_volume":"5665052","average_volume":"9218444","executed":"2018-09-05 12:55:34"}, {"symbol":"JISLJALEQS","current_candlestick_pattern":"","no_of_dry_day":"3","percentage_increase_volume":"0.00","previous_candlestick_pattern":"Bearish Engulfing Pattern","previous_candlestick_pattern_date":"2018-09-04 00:00:00","current_volume":"3101744","average_volume":"7489729","executed":"2018-09-05 12:55:34"}, {"symbol":"JPASSOCIAT","current_candlestick_pattern":"","no_of_dry_day":"3","percentage_increase_volume":"0.00","previous_candlestick_pattern":"Bearish Engulfing Pattern","previous_candlestick_pattern_date":"2018-09-03 00:00:00","current_volume":"24019273","average_volume":"62548350","executed":"2018-09-05 12:55:34"}, {"symbol":"JSWSTEEL","current_candlestick_pattern":"Piercing Pattern ","no_of_dry_day":"3","percentage_increase_volume":"0.00","previous_candlestick_pattern":"Shooting Star","previous_candlestick_pattern_date":"2018-08-30 00:00:00","current_volume":"3191979","average_volume":"12075950","executed":"2018-09-05 12:55:34"}, {"symbol":"JUBLFOOD","current_candlestick_pattern":"","no_of_dry_day":"0","percentage_increase_volume":"0.00","previous_candlestick_pattern":"Bearish Engulfing Pattern","previous_candlestick_pattern_date":"2018-09-03 00:00:00","current_volume":"818450","average_volume":"997332","executed":"2018-09-05 12:55:30"}, {"symbol":"JUSTDIAL","current_candlestick_pattern":"","no_of_dry_day":"0","percentage_increase_volume":"0.00","previous_candlestick_pattern":"Bearish Engulfing Pattern","previous_candlestick_pattern_date":"2018-09-03 00:00:00","current_volume":"639246","average_volume":"1329310","executed":"2018-09-05 12:55:30"}, {"symbol":"KAJARIACER","current_candlestick_pattern":"","no_of_dry_day":"7","percentage_increase_volume":"0.00","previous_candlestick_pattern":"Bearish Engulfing Pattern","previous_candlestick_pattern_date":"2018-09-04 00:00:00","current_volume":"482111","average_volume":"1699750","executed":"2018-09-05 12:55:34"}, {"symbol":"KOTAKBANK","current_candlestick_pattern":"","no_of_dry_day":"1","percentage_increase_volume":"0.00","previous_candlestick_pattern":"Bearish Engulfing Pattern","previous_candlestick_pattern_date":"2018-09-03 00:00:00","current_volume":"916596","average_volume":"1988553","executed":"2018-09-05 12:55:30"}, {"symbol":"KPIT","current_candlestick_pattern":"Bearish One Black Crow ","no_of_dry_day":"0","percentage_increase_volume":"0.00","previous_candlestick_pattern":"Shooting Star","previous_candlestick_pattern_date":"2018-09-04 00:00:00","current_volume":"1078740","average_volume":"1911722","executed":"2018-09-05 12:55:30"}, {"symbol":"KSCL","current_candlestick_pattern":"Bullish Harami Pattern Piercing Pattern ","no_of_dry_day":"0","percentage_increase_volume":"0.00","previous_candlestick_pattern":"Shooting Star","previous_candlestick_pattern_date":"2018-08-31 00:00:00","current_volume":"224365","average_volume":"521656","executed":"2018-09-05 12:55:30"}, {"symbol":"KTKBANK","current_candlestick_pattern":"","no_of_dry_day":"9","percentage_increase_volume":"0.00","previous_candlestick_pattern":"Bearish Evening Star Pattern","previous_candlestick_pattern_date":"2018-09-04 00:00:00","current_volume":"1061860","average_volume":"1707464","executed":"2018-09-05 12:55:34"}, {"symbol":"L&TFH","current_candlestick_pattern":"","no_of_dry_day":"0","percentage_increase_volume":"0.00","previous_candlestick_pattern":"Bearish Engulfing Pattern","previous_candlestick_pattern_date":"2018-08-30 00:00:00","current_volume":"3814843","average_volume":"5578754","executed":"2018-09-05 12:55:34"}, {"symbol":"LICHSGFIN","current_candlestick_pattern":"","no_of_dry_day":"3","percentage_increase_volume":"0.00","previous_candlestick_pattern":"Bearish Engulfing Pattern","previous_candlestick_pattern_date":"2018-08-31 00:00:00","current_volume":"1734269","average_volume":"3609125","executed":"2018-09-05 12:55:30"}, {"symbol":"LT","current_candlestick_pattern":"","no_of_dry_day":"8","percentage_increase_volume":"0.00","previous_candlestick_pattern":"Bullish One White Soldier","previous_candlestick_pattern_date":"2018-08-31 00:00:00","current_volume":"1279910","average_volume":"2865865","executed":"2018-09-05 12:55:30"}, {"symbol":"LUPIN","current_candlestick_pattern":"","no_of_dry_day":"1","percentage_increase_volume":"0.00","previous_candlestick_pattern":"Shooting Star","previous_candlestick_pattern_date":"2018-09-03 00:00:00","current_volume":"2012839","average_volume":"3438212","executed":"2018-09-05 12:55:30"}, {"symbol":"M&M","current_candlestick_pattern":"Shooting Star ","no_of_dry_day":"0","percentage_increase_volume":"0.00","previous_candlestick_pattern":"Bullish One White Soldier","previous_candlestick_pattern_date":"2018-08-29 00:00:00","current_volume":"928486","average_volume":"1776495","executed":"2018-09-05 12:55:30"}, {"symbol":"M&MFIN","current_candlestick_pattern":"","no_of_dry_day":"0","percentage_increase_volume":"0.00","previous_candlestick_pattern":"Paper Umbrella","previous_candlestick_pattern_date":"2018-08-31 00:00:00","current_volume":"1474440","average_volume":"1516954","executed":"2018-09-05 12:55:30"}, {"symbol":"MANAPPURAM","current_candlestick_pattern":"Bullish Harami Pattern Piercing Pattern ","no_of_dry_day":"0","percentage_increase_volume":"0.00","previous_candlestick_pattern":"Bullish Harami Pattern","previous_candlestick_pattern_date":"2018-08-29 00:00:00","current_volume":"1481027","average_volume":"1967639","executed":"2018-09-05 12:55:34"}, {"symbol":"MARICO","current_candlestick_pattern":"","no_of_dry_day":"2","percentage_increase_volume":"0.00","previous_candlestick_pattern":"Shooting Star","previous_candlestick_pattern_date":"2018-08-30 00:00:00","current_volume":"587073","average_volume":"2130447","executed":"2018-09-05 12:55:34"}, {"symbol":"MARUTI","current_candlestick_pattern":"","no_of_dry_day":"1","percentage_increase_volume":"0.00","previous_candlestick_pattern":"Bearish Harami Pattern","previous_candlestick_pattern_date":"2018-08-29 00:00:00","current_volume":"204540","average_volume":"563374","executed":"2018-09-05 12:55:30"}, {"symbol":"MCDOWELL-N","current_candlestick_pattern":"","no_of_dry_day":"2","percentage_increase_volume":"0.00","previous_candlestick_pattern":"Bearish Engulfing Pattern","previous_candlestick_pattern_date":"2018-08-31 00:00:00","current_volume":"512639","average_volume":"1188432","executed":"2018-09-05 12:55:34"}, {"symbol":"MCX","current_candlestick_pattern":"","no_of_dry_day":"0","percentage_increase_volume":"0.00","previous_candlestick_pattern":"","previous_candlestick_pattern_date":"0000-00-00 00:00:00","current_volume":"304091","average_volume":"371795","executed":"2018-09-05 12:55:34"}, {"symbol":"MFSL","current_candlestick_pattern":"","no_of_dry_day":"2","percentage_increase_volume":"0.00","previous_candlestick_pattern":"Bearish Engulfing Pattern","previous_candlestick_pattern_date":"2018-08-29 00:00:00","current_volume":"249997","average_volume":"400292","executed":"2018-09-05 12:55:34"}, {"symbol":"MGL","current_candlestick_pattern":"","no_of_dry_day":"8","percentage_increase_volume":"0.00","previous_candlestick_pattern":"Piercing Pattern","previous_candlestick_pattern_date":"2018-08-29 00:00:00","current_volume":"321380","average_volume":"3846608","executed":"2018-09-05 12:55:30"}, {"symbol":"MINDTREE","current_candlestick_pattern":"","no_of_dry_day":"0","percentage_increase_volume":"0.00","previous_candlestick_pattern":"Bullish Harami Pattern","previous_candlestick_pattern_date":"2018-09-04 00:00:00","current_volume":"1126599","average_volume":"1873619","executed":"2018-09-05 12:55:30"}, {"symbol":"MOTHERSUMI","current_candlestick_pattern":"","no_of_dry_day":"0","percentage_increase_volume":"0.00","previous_candlestick_pattern":"Bearish Harami Pattern","previous_candlestick_pattern_date":"2018-08-30 00:00:00","current_volume":"1414357","average_volume":"2773287","executed":"2018-09-05 12:55:34"}, {"symbol":"MRF","current_candlestick_pattern":"","no_of_dry_day":"0","percentage_increase_volume":"0.00","previous_candlestick_pattern":"Bearish One Black Crow","previous_candlestick_pattern_date":"2018-09-03 00:00:00","current_volume":"4154","average_volume":"4530","executed":"2018-09-05 12:55:30"}, {"symbol":"MRPL","current_candlestick_pattern":"","no_of_dry_day":"0","percentage_increase_volume":"0.00","previous_candlestick_pattern":"Bullish Harami Pattern","previous_candlestick_pattern_date":"2018-08-30 00:00:00","current_volume":"814935","average_volume":"1029287","executed":"2018-09-05 12:55:34"}, {"symbol":"MUTHOOTFIN","current_candlestick_pattern":"Bullish One White Soldier ","no_of_dry_day":"0","percentage_increase_volume":"553.91","previous_candlestick_pattern":"Bearish Engulfing Pattern","previous_candlestick_pattern_date":"2018-08-30 00:00:00","current_volume":"7285170","average_volume":"1114100","executed":"2018-09-05 12:55:30"}, {"symbol":"NATIONALUM","current_candlestick_pattern":"Bullish Harami Pattern ","no_of_dry_day":"3","percentage_increase_volume":"0.00","previous_candlestick_pattern":"Paper Umbrella","previous_candlestick_pattern_date":"2018-08-28 00:00:00","current_volume":"5666797","average_volume":"11182756","executed":"2018-09-05 12:55:34"}, {"symbol":"NBCC","current_candlestick_pattern":"","no_of_dry_day":"0","percentage_increase_volume":"0.00","previous_candlestick_pattern":"Bearish Engulfing Pattern","previous_candlestick_pattern_date":"2018-09-04 00:00:00","current_volume":"2978058","average_volume":"3828640","executed":"2018-09-05 12:55:30"}, {"symbol":"NCC","current_candlestick_pattern":"","no_of_dry_day":"0","percentage_increase_volume":"48.70","previous_candlestick_pattern":"Bearish Engulfing Pattern","previous_candlestick_pattern_date":"2018-09-04 00:00:00","current_volume":"14895719","average_volume":"10017401","executed":"2018-09-05 12:55:30"}, {"symbol":"NESTLEIND","current_candlestick_pattern":"","no_of_dry_day":"2","percentage_increase_volume":"0.00","previous_candlestick_pattern":"Bearish Engulfing Pattern","previous_candlestick_pattern_date":"2018-09-03 00:00:00","current_volume":"45109","average_volume":"83726","executed":"2018-09-05 12:55:30"}, {"symbol":"NHPC","current_candlestick_pattern":"","no_of_dry_day":"0","percentage_increase_volume":"0.00","previous_candlestick_pattern":"Bearish Engulfing Pattern","previous_candlestick_pattern_date":"2018-09-04 00:00:00","current_volume":"1414286","average_volume":"2453678","executed":"2018-09-05 12:55:30"}, {"symbol":"NIITTECH","current_candlestick_pattern":"","no_of_dry_day":"2","percentage_increase_volume":"0.00","previous_candlestick_pattern":"Bullish One White Soldier","previous_candlestick_pattern_date":"2018-08-30 00:00:00","current_volume":"491623","average_volume":"822332","executed":"2018-09-05 12:55:30"}, {"symbol":"NMDC","current_candlestick_pattern":"","no_of_dry_day":"0","percentage_increase_volume":"0.00","previous_candlestick_pattern":"Shooting Star","previous_candlestick_pattern_date":"2018-08-29 00:00:00","current_volume":"2043532","average_volume":"3709870","executed":"2018-09-05 12:55:34"}, {"symbol":"NTPC","current_candlestick_pattern":"","no_of_dry_day":"2","percentage_increase_volume":"0.00","previous_candlestick_pattern":"Bullish Engulfing Pattern","previous_candlestick_pattern_date":"2018-08-30 00:00:00","current_volume":"699212","average_volume":"4878917","executed":"2018-09-05 12:55:30"}, {"symbol":"OFSS","current_candlestick_pattern":"Bullish Harami Pattern Piercing Pattern ","no_of_dry_day":"1","percentage_increase_volume":"0.00","previous_candlestick_pattern":"Bearish Engulfing Pattern","previous_candlestick_pattern_date":"2018-09-03 00:00:00","current_volume":"41272","average_volume":"89583","executed":"2018-09-05 12:55:30"}, {"symbol":"OIL","current_candlestick_pattern":"","no_of_dry_day":"2","percentage_increase_volume":"0.00","previous_candlestick_pattern":"Bearish Engulfing Pattern","previous_candlestick_pattern_date":"2018-09-03 00:00:00","current_volume":"522021","average_volume":"603881","executed":"2018-09-05 12:55:30"}, {"symbol":"ONGC","current_candlestick_pattern":"","no_of_dry_day":"2","percentage_increase_volume":"0.00","previous_candlestick_pattern":"Bearish Engulfing Pattern","previous_candlestick_pattern_date":"2018-09-03 00:00:00","current_volume":"1860151","average_volume":"5995968","executed":"2018-09-05 12:55:34"}, {"symbol":"ORIENTBANK","current_candlestick_pattern":"","no_of_dry_day":"0","percentage_increase_volume":"0.00","previous_candlestick_pattern":"Shooting Star","previous_candlestick_pattern_date":"2018-09-03 00:00:00","current_volume":"2523972","average_volume":"4684005","executed":"2018-09-05 12:55:34"}, {"symbol":"PAGEIND","current_candlestick_pattern":"","no_of_dry_day":"2","percentage_increase_volume":"0.00","previous_candlestick_pattern":"Bearish Engulfing Pattern","previous_candlestick_pattern_date":"2018-08-29 00:00:00","current_volume":"15661","average_volume":"91077","executed":"2018-09-05 12:55:30"}, {"symbol":"PCJEWELLER","current_candlestick_pattern":"","no_of_dry_day":"0","percentage_increase_volume":"0.00","previous_candlestick_pattern":"Bullish One White Soldier","previous_candlestick_pattern_date":"2018-09-03 00:00:00","current_volume":"5831889","average_volume":"13340847","executed":"2018-09-05 12:55:30"}, {"symbol":"PEL","current_candlestick_pattern":"","no_of_dry_day":"2","percentage_increase_volume":"0.00","previous_candlestick_pattern":"Bearish Engulfing Pattern","previous_candlestick_pattern_date":"2018-09-03 00:00:00","current_volume":"195137","average_volume":"581963","executed":"2018-09-05 12:55:34"}, {"symbol":"PETRONET","current_candlestick_pattern":"Piercing Pattern ","no_of_dry_day":"2","percentage_increase_volume":"0.00","previous_candlestick_pattern":"Piercing Pattern","previous_candlestick_pattern_date":"2018-08-29 00:00:00","current_volume":"1586583","average_volume":"3332501","executed":"2018-09-05 12:55:34"}, {"symbol":"PFC","current_candlestick_pattern":"Shooting Star ","no_of_dry_day":"4","percentage_increase_volume":"0.00","previous_candlestick_pattern":"","previous_candlestick_pattern_date":"0000-00-00 00:00:00","current_volume":"4578384","average_volume":"8024648","executed":"2018-09-05 12:55:34"}, {"symbol":"PIDILITIND","current_candlestick_pattern":"Piercing Pattern ","no_of_dry_day":"2","percentage_increase_volume":"0.00","previous_candlestick_pattern":"Bullish One White Soldier","previous_candlestick_pattern_date":"2018-08-31 00:00:00","current_volume":"371612","average_volume":"537815","executed":"2018-09-05 12:55:30"}, {"symbol":"PNB","current_candlestick_pattern":"","no_of_dry_day":"2","percentage_increase_volume":"0.00","previous_candlestick_pattern":"Bullish Harami Pattern","previous_candlestick_pattern_date":"2018-08-29 00:00:00","current_volume":"12312550","average_volume":"31815779","executed":"2018-09-05 12:55:34"}, {"symbol":"POWERGRID","current_candlestick_pattern":"Bullish Engulfing Pattern ","no_of_dry_day":"2","percentage_increase_volume":"0.00","previous_candlestick_pattern":"Bearish Engulfing Pattern","previous_candlestick_pattern_date":"2018-09-03 00:00:00","current_volume":"2114990","average_volume":"5591671","executed":"2018-09-05 12:55:30"}, {"symbol":"PTC","current_candlestick_pattern":"","no_of_dry_day":"0","percentage_increase_volume":"0.00","previous_candlestick_pattern":"Bearish Engulfing Pattern","previous_candlestick_pattern_date":"2018-09-04 00:00:00","current_volume":"1219454","average_volume":"2887004","executed":"2018-09-05 12:55:34"}, {"symbol":"PVR","current_candlestick_pattern":"","no_of_dry_day":"0","percentage_increase_volume":"0.00","previous_candlestick_pattern":"Bearish Engulfing Pattern","previous_candlestick_pattern_date":"2018-09-04 00:00:00","current_volume":"181127","average_volume":"432318","executed":"2018-09-05 12:55:30"}, {"symbol":"RAMCOCEM","current_candlestick_pattern":"","no_of_dry_day":"3","percentage_increase_volume":"0.00","previous_candlestick_pattern":"Shooting Star","previous_candlestick_pattern_date":"2018-08-28 00:00:00","current_volume":"230243","average_volume":"274280","executed":"2018-09-05 12:55:30"}, {"symbol":"RAYMOND","current_candlestick_pattern":"","no_of_dry_day":"5","percentage_increase_volume":"0.00","previous_candlestick_pattern":"Bullish One White Soldier","previous_candlestick_pattern_date":"2018-08-30 00:00:00","current_volume":"859239","average_volume":"990538","executed":"2018-09-05 12:55:34"}, {"symbol":"RBLBANK","current_candlestick_pattern":"","no_of_dry_day":"4","percentage_increase_volume":"0.00","previous_candlestick_pattern":"Bearish Engulfing Pattern","previous_candlestick_pattern_date":"2018-09-03 00:00:00","current_volume":"659729","average_volume":"2166610","executed":"2018-09-05 12:55:30"}, {"symbol":"RCOM","current_candlestick_pattern":"","no_of_dry_day":"4","percentage_increase_volume":"0.00","previous_candlestick_pattern":"Bearish Engulfing Pattern","previous_candlestick_pattern_date":"2018-09-04 00:00:00","current_volume":"56734627","average_volume":"91796285","executed":"2018-09-05 12:55:34"}, {"symbol":"RECLTD","current_candlestick_pattern":"","no_of_dry_day":"2","percentage_increase_volume":"0.00","previous_candlestick_pattern":"Bullish One White Soldier","previous_candlestick_pattern_date":"2018-08-29 00:00:00","current_volume":"2659270","average_volume":"6470791","executed":"2018-09-05 12:55:34"}, {"symbol":"RELCAPITAL","current_candlestick_pattern":"","no_of_dry_day":"1","percentage_increase_volume":"0.00","previous_candlestick_pattern":"Bearish One Black Crow","previous_candlestick_pattern_date":"2018-09-04 00:00:00","current_volume":"2566429","average_volume":"4757221","executed":"2018-09-05 12:55:30"}, {"symbol":"RELIANCE","current_candlestick_pattern":"Bearish Engulfing Pattern ","no_of_dry_day":"1","percentage_increase_volume":"0.00","previous_candlestick_pattern":"Bullish Harami Pattern","previous_candlestick_pattern_date":"2018-09-04 00:00:00","current_volume":"4192991","average_volume":"9035194","executed":"2018-09-05 12:55:30"}, {"symbol":"RELINFRA","current_candlestick_pattern":"Piercing Pattern ","no_of_dry_day":"1","percentage_increase_volume":"0.00","previous_candlestick_pattern":"Bullish Engulfing Pattern","previous_candlestick_pattern_date":"2018-08-29 00:00:00","current_volume":"2472125","average_volume":"5503205","executed":"2018-09-05 12:55:30"}, {"symbol":"REPCOHOME","current_candlestick_pattern":"Bearish Engulfing Pattern ","no_of_dry_day":"1","percentage_increase_volume":"0.00","previous_candlestick_pattern":"Bearish Engulfing Pattern","previous_candlestick_pattern_date":"2018-08-30 00:00:00","current_volume":"57156","average_volume":"306963","executed":"2018-09-05 12:55:30"}, {"symbol":"RPOWER","current_candlestick_pattern":"","no_of_dry_day":"1","percentage_increase_volume":"0.00","previous_candlestick_pattern":"Shooting Star","previous_candlestick_pattern_date":"2018-09-03 00:00:00","current_volume":"5566242","average_volume":"12804858","executed":"2018-09-05 12:55:30"}, {"symbol":"SAIL","current_candlestick_pattern":"","no_of_dry_day":"3","percentage_increase_volume":"0.00","previous_candlestick_pattern":"Bearish Engulfing Pattern","previous_candlestick_pattern_date":"2018-09-04 00:00:00","current_volume":"4681449","average_volume":"11537219","executed":"2018-09-05 12:55:30"}, {"symbol":"SBIN","current_candlestick_pattern":"","no_of_dry_day":"0","percentage_increase_volume":"0.00","previous_candlestick_pattern":"Bearish Engulfing Pattern","previous_candlestick_pattern_date":"2018-09-03 00:00:00","current_volume":"10722632","average_volume":"21723928","executed":"2018-09-05 12:55:34"}, {"symbol":"SHREECEM","current_candlestick_pattern":"","no_of_dry_day":"4","percentage_increase_volume":"0.00","previous_candlestick_pattern":"Paper Umbrella","previous_candlestick_pattern_date":"2018-08-31 00:00:00","current_volume":"5054","average_volume":"19645","executed":"2018-09-05 12:55:30"}, {"symbol":"SIEMENS","current_candlestick_pattern":"","no_of_dry_day":"9","percentage_increase_volume":"0.00","previous_candlestick_pattern":"Bullish Harami Pattern","previous_candlestick_pattern_date":"2018-08-31 00:00:00","current_volume":"88219","average_volume":"204057","executed":"2018-09-05 12:55:30"}, {"symbol":"SOUTHBANK","current_candlestick_pattern":"","no_of_dry_day":"0","percentage_increase_volume":"0.00","previous_candlestick_pattern":"Bearish Engulfing Pattern","previous_candlestick_pattern_date":"2018-09-04 00:00:00","current_volume":"10197173","average_volume":"11948108","executed":"2018-09-05 12:55:34"}, {"symbol":"SREINFRA","current_candlestick_pattern":"Piercing Pattern ","no_of_dry_day":"2","percentage_increase_volume":"0.00","previous_candlestick_pattern":"Bearish One Black Crow","previous_candlestick_pattern_date":"2018-09-03 00:00:00","current_volume":"4171873","average_volume":"5504026","executed":"2018-09-05 12:55:30"}, {"symbol":"SRF","current_candlestick_pattern":"","no_of_dry_day":"2","percentage_increase_volume":"0.00","previous_candlestick_pattern":"Bullish One White Soldier","previous_candlestick_pattern_date":"2018-08-29 00:00:00","current_volume":"130497","average_volume":"311267","executed":"2018-09-05 12:55:30"}, {"symbol":"SRTRANSFIN","current_candlestick_pattern":"","no_of_dry_day":"1","percentage_increase_volume":"0.00","previous_candlestick_pattern":"Bearish Engulfing Pattern","previous_candlestick_pattern_date":"2018-09-03 00:00:00","current_volume":"938609","average_volume":"1104494","executed":"2018-09-05 12:55:34"}, {"symbol":"STAR","current_candlestick_pattern":"Piercing Pattern ","no_of_dry_day":"1","percentage_increase_volume":"0.00","previous_candlestick_pattern":"Bearish Engulfing Pattern","previous_candlestick_pattern_date":"2018-09-04 00:00:00","current_volume":"1635746","average_volume":"2506013","executed":"2018-09-05 12:55:34"}, {"symbol":"SUNPHARMA","current_candlestick_pattern":"Shooting Star Bullish Engulfing Pattern ","no_of_dry_day":"1","percentage_increase_volume":"0.00","previous_candlestick_pattern":"Bullish One White Soldier","previous_candlestick_pattern_date":"2018-08-30 00:00:00","current_volume":"5856303","average_volume":"8174972","executed":"2018-09-05 12:55:30"}, {"symbol":"SUNTV","current_candlestick_pattern":"","no_of_dry_day":"0","percentage_increase_volume":"0.00","previous_candlestick_pattern":"Bearish One Black Crow","previous_candlestick_pattern_date":"2018-09-04 00:00:00","current_volume":"1294724","average_volume":"1607883","executed":"2018-09-05 12:55:30"}, {"symbol":"SUZLON","current_candlestick_pattern":"","no_of_dry_day":"0","percentage_increase_volume":"0.00","previous_candlestick_pattern":"","previous_candlestick_pattern_date":"0000-00-00 00:00:00","current_volume":"20082720","average_volume":"20470121","executed":"2018-09-05 12:55:34"}, {"symbol":"SYNDIBANK","current_candlestick_pattern":"","no_of_dry_day":"0","percentage_increase_volume":"0.00","previous_candlestick_pattern":"Bearish One Black Crow","previous_candlestick_pattern_date":"2018-09-04 00:00:00","current_volume":"3290400","average_volume":"3743114","executed":"2018-09-05 12:55:34"}, {"symbol":"TATACHEM","current_candlestick_pattern":"","no_of_dry_day":"6","percentage_increase_volume":"0.00","previous_candlestick_pattern":"Bearish One Black Crow","previous_candlestick_pattern_date":"2018-09-04 00:00:00","current_volume":"488867","average_volume":"1016934","executed":"2018-09-05 12:55:30"}, {"symbol":"TATACOMM","current_candlestick_pattern":"","no_of_dry_day":"0","percentage_increase_volume":"0.00","previous_candlestick_pattern":"Bearish Engulfing Pattern","previous_candlestick_pattern_date":"2018-08-31 00:00:00","current_volume":"287274","average_volume":"331432","executed":"2018-09-05 12:55:30"}, {"symbol":"TATAELXSI","current_candlestick_pattern":"","no_of_dry_day":"0","percentage_increase_volume":"0.00","previous_candlestick_pattern":"Bearish Engulfing Pattern","previous_candlestick_pattern_date":"2018-09-04 00:00:00","current_volume":"309654","average_volume":"553650","executed":"2018-09-05 12:55:30"}, {"symbol":"TATAGLOBAL","current_candlestick_pattern":"","no_of_dry_day":"0","percentage_increase_volume":"0.00","previous_candlestick_pattern":"Bearish Engulfing Pattern","previous_candlestick_pattern_date":"2018-09-04 00:00:00","current_volume":"1562100","average_volume":"2478680","executed":"2018-09-05 12:55:34"}, {"symbol":"TATAMOTORS","current_candlestick_pattern":"","no_of_dry_day":"0","percentage_increase_volume":"0.00","previous_candlestick_pattern":"Bullish Engulfing Pattern","previous_candlestick_pattern_date":"2018-08-31 00:00:00","current_volume":"4091719","average_volume":"9928231","executed":"2018-09-05 12:55:30"}, {"symbol":"TATAMTRDVR","current_candlestick_pattern":"","no_of_dry_day":"0","percentage_increase_volume":"0.00","previous_candlestick_pattern":"Bearish Engulfing Pattern","previous_candlestick_pattern_date":"2018-09-04 00:00:00","current_volume":"1349833","average_volume":"2621231","executed":"2018-09-05 12:55:34"}, {"symbol":"TATAPOWER","current_candlestick_pattern":"Shooting Star ","no_of_dry_day":"0","percentage_increase_volume":"0.00","previous_candlestick_pattern":"Bearish Engulfing Pattern","previous_candlestick_pattern_date":"2018-09-04 00:00:00","current_volume":"1932296","average_volume":"5679505","executed":"2018-09-05 12:55:34"}, {"symbol":"TATASTEEL","current_candlestick_pattern":"","no_of_dry_day":"0","percentage_increase_volume":"0.00","previous_candlestick_pattern":"","previous_candlestick_pattern_date":"0000-00-00 00:00:00","current_volume":"0","average_volume":"0","executed":"2018-09-05 12:55:30"}, {"symbol":"TCS","current_candlestick_pattern":"","no_of_dry_day":"0","percentage_increase_volume":"0.00","previous_candlestick_pattern":"Bullish One White Soldier","previous_candlestick_pattern_date":"2018-09-04 00:00:00","current_volume":"816583","average_volume":"2125355","executed":"2018-09-05 12:55:34"}, {"symbol":"TECHM","current_candlestick_pattern":"","no_of_dry_day":"2","percentage_increase_volume":"0.00","previous_candlestick_pattern":"Bullish Harami Pattern","previous_candlestick_pattern_date":"2018-09-04 00:00:00","current_volume":"3752439","average_volume":"4897153","executed":"2018-09-05 12:55:30"}, {"symbol":"TITAN","current_candlestick_pattern":"","no_of_dry_day":"0","percentage_increase_volume":"0.00","previous_candlestick_pattern":"Bearish Engulfing Pattern","previous_candlestick_pattern_date":"2018-09-04 00:00:00","current_volume":"1712410","average_volume":"2600671","executed":"2018-09-05 12:55:30"}, {"symbol":"TORNTPHARM","current_candlestick_pattern":"","no_of_dry_day":"2","percentage_increase_volume":"0.00","previous_candlestick_pattern":"Paper Umbrella","previous_candlestick_pattern_date":"2018-08-30 00:00:00","current_volume":"109648","average_volume":"281495","executed":"2018-09-05 12:55:34"}, {"symbol":"TORNTPOWER","current_candlestick_pattern":"","no_of_dry_day":"5","percentage_increase_volume":"0.00","previous_candlestick_pattern":"Bullish One White Soldier","previous_candlestick_pattern_date":"2018-08-27 00:00:00","current_volume":"419671","average_volume":"1534869","executed":"2018-09-05 12:55:34"}, {"symbol":"TV18BRDCST","current_candlestick_pattern":"","no_of_dry_day":"0","percentage_increase_volume":"0.00","previous_candlestick_pattern":"Bearish Engulfing Pattern","previous_candlestick_pattern_date":"2018-09-04 00:00:00","current_volume":"5386844","average_volume":"5520003","executed":"2018-09-05 12:55:30"}, {"symbol":"TVSMOTOR","current_candlestick_pattern":"Shooting Star Piercing Pattern ","no_of_dry_day":"0","percentage_increase_volume":"0.00","previous_candlestick_pattern":"Bullish Harami Pattern","previous_candlestick_pattern_date":"2018-08-30 00:00:00","current_volume":"693635","average_volume":"1786594","executed":"2018-09-05 12:55:30"}, {"symbol":"UBL","current_candlestick_pattern":"","no_of_dry_day":"3","percentage_increase_volume":"0.00","previous_candlestick_pattern":"Bearish Harami Pattern","previous_candlestick_pattern_date":"2018-08-31 00:00:00","current_volume":"460762","average_volume":"801087","executed":"2018-09-05 12:55:34"}, {"symbol":"UJJIVAN","current_candlestick_pattern":"","no_of_dry_day":"0","percentage_increase_volume":"0.00","previous_candlestick_pattern":"Bearish Engulfing Pattern","previous_candlestick_pattern_date":"2018-09-04 00:00:00","current_volume":"411336","average_volume":"965336","executed":"2018-09-05 12:55:34"}, {"symbol":"ULTRACEMCO","current_candlestick_pattern":"","no_of_dry_day":"0","percentage_increase_volume":"0.00","previous_candlestick_pattern":"Bearish One Black Crow","previous_candlestick_pattern_date":"2018-09-03 00:00:00","current_volume":"172709","average_volume":"239064","executed":"2018-09-05 12:55:34"}, {"symbol":"UNIONBANK","current_candlestick_pattern":"","no_of_dry_day":"0","percentage_increase_volume":"0.00","previous_candlestick_pattern":"Shooting Star","previous_candlestick_pattern_date":"2018-09-03 00:00:00","current_volume":"6959030","average_volume":"10050977","executed":"2018-09-05 12:55:34"}, {"symbol":"UPL","current_candlestick_pattern":"Bullish Harami Pattern Piercing Pattern ","no_of_dry_day":"2","percentage_increase_volume":"0.00","previous_candlestick_pattern":"Bearish One Black Crow","previous_candlestick_pattern_date":"2018-09-04 00:00:00","current_volume":"2384336","average_volume":"3525165","executed":"2018-09-05 12:55:30"}, {"symbol":"VEDL","current_candlestick_pattern":"","no_of_dry_day":"3","percentage_increase_volume":"0.00","previous_candlestick_pattern":"Bearish One Black Crow","previous_candlestick_pattern_date":"2018-08-31 00:00:00","current_volume":"4825852","average_volume":"14149131","executed":"2018-09-05 12:55:34"}, {"symbol":"VGUARD","current_candlestick_pattern":"","no_of_dry_day":"2","percentage_increase_volume":"0.00","previous_candlestick_pattern":"Bearish Engulfing Pattern","previous_candlestick_pattern_date":"2018-09-03 00:00:00","current_volume":"505725","average_volume":"1280841","executed":"2018-09-05 12:55:30"}, {"symbol":"VOLTAS","current_candlestick_pattern":"Bearish One Black Crow ","no_of_dry_day":"3","percentage_increase_volume":"0.00","previous_candlestick_pattern":"Shooting Star","previous_candlestick_pattern_date":"2018-09-04 00:00:00","current_volume":"1003067","average_volume":"1422484","executed":"2018-09-05 12:55:30"}, {"symbol":"WIPRO","current_candlestick_pattern":"","no_of_dry_day":"0","percentage_increase_volume":"0.00","previous_candlestick_pattern":"Bullish Harami Pattern","previous_candlestick_pattern_date":"2018-09-04 00:00:00","current_volume":"5930605","average_volume":"6266906","executed":"2018-09-05 12:55:30"}, {"symbol":"WOCKPHARMA","current_candlestick_pattern":"Piercing Pattern ","no_of_dry_day":"1","percentage_increase_volume":"0.00","previous_candlestick_pattern":"Piercing Pattern","previous_candlestick_pattern_date":"2018-08-29 00:00:00","current_volume":"862374","average_volume":"1413010","executed":"2018-09-05 12:55:30"}, {"symbol":"YESBANK","current_candlestick_pattern":"Piercing Pattern ","no_of_dry_day":"2","percentage_increase_volume":"0.00","previous_candlestick_pattern":"Bearish Engulfing Pattern","previous_candlestick_pattern_date":"2018-09-03 00:00:00","current_volume":"13415380","average_volume":"26576785","executed":"2018-09-05 12:55:34"}, {"symbol":"ZEEL","current_candlestick_pattern":"","no_of_dry_day":"2","percentage_increase_volume":"0.00","previous_candlestick_pattern":"Bearish Engulfing Pattern","previous_candlestick_pattern_date":"2018-08-31 00:00:00","current_volume":"669615","average_volume":"1586180","executed":"2018-09-05 12:55:30"}]
